Workbook

Sheet Project Tracker
A1: EMS — Developer Implementation Tracker
A2: Grounded in the EMS FRD and Database ER Diagram — every task names the real table, entity, API and screen involved. Includes GL Account Management (new). | Total estimated effort: 837 hours (incl. RBAC & GL Account)
A4: Task ID | B4: Epic | C4: User Story | D4: Task | E4: Task Description | F4: Category | G4: Sprint | H4: Due Date | I4: Dependency | J4: Est. Hours | K4: Actual Hours | L4: Priority | M4: Assignee | N4: Status | O4: Acceptance Criteria
A5: T-001 | B5: EP01 - Expense Management System Foundation & Administration | C5: EP01-S1 - Configure GL Account Management | D5: Design gl_account database table | E5: Design the `gl_account` database table. Columns: gl_account_id, gl_account_code, gl_account_name, account_type, description, status, created_at, updated_at. Purpose: Maintain the General Ledger Account master that Expense Categories (and, downstream, Finance/Invoice postings) reference, so GL mapping is a governed, reusable master-data relationship rather than ... | F5: Database | G5: Sprint 1 | H5: 2026-08-23 | I5: Project start (no dependency) | J5: 0.86 | L5: High | N5: Not Started | O5: - GL Account code must be unique per organization; duplicate detection is case-insensitive - Only Active GL Accounts are selectable in any downstream dropdown (e.g., Expense Category form) - A GL Account cannot be deleted while mapped to one or more Expense Categories - Administrator creates a GL Account with a unique code, name, and account type - Admin can create/edit/deactivate a GL Account with a unique code, name and account type - Unit tests passed - UI integrated successfully
A6: T-002 | B6: EP01 - Expense Management System Foundation & Administration | C6: EP01-S1 - Configure GL Account Management | D6: Create GLAccount JPA Entity | E6: Create the GLAccount JPA entity mapped 1:1 to `gl_account`, with fields for gl_account_id, gl_account_code, gl_account_name, account_type, description, status, created_at, updated_at, standard audit columns (created_at, updated_at), and a unique constraint on gl_account_code. | F6: Database | G6: Sprint 1 | H6: 2026-08-23 | I6: gl_account table created (T-001) | J6: 0.97 | L6: High | N6: Not Started | O6: - GL Account code must be unique per organization; duplicate detection is case-insensitive - Only Active GL Accounts are selectable in any downstream dropdown (e.g., Expense Category form) - A GL Account cannot be deleted while mapped to one or more Expense Categories - Administrator creates a GL Account with a unique code, name, and account type - Admin can create/edit/deactivate a GL Account with a unique code, name and account type - Unit tests passed - UI integrated successfully
A7: T-003 | B7: EP01 - Expense Management System Foundation & Administration | C7: EP01-S1 - Configure GL Account Management | D7: Create GLAccountRepository | E7: Create GLAccountRepository with standard CRUD operations plus custom queries for active GL Accounts and case-insensitive duplicate-code lookup. | F7: Backend | G7: Sprint 1 | H7: 2026-08-23 | I7: GLAccount entity completed (T-002) | J7: 0.97 | L7: High | N7: Not Started | O7: - GL Account code must be unique per organization; duplicate detection is case-insensitive - Only Active GL Accounts are selectable in any downstream dropdown (e.g., Expense Category form) - A GL Account cannot be deleted while mapped to one or more Expense Categories - Administrator creates a GL Account with a unique code, name, and account type - Admin can create/edit/deactivate a GL Account with a unique code, name and account type - Unit tests passed - UI integrated successfully
A8: T-004 | B8: EP01 - Expense Management System Foundation & Administration | C8: EP01-S1 - Configure GL Account Management | D8: Create GL Account Request & Response DTOs | E8: Create GLAccountRequest and GLAccountResponse DTOs covering gl_account_id, gl_account_code, gl_account_name, account_type, description, status, created_at, updated_at, with the Response DTO also exposing a `mappedCategoryCount` field so the UI can show/block deletion of mapped accounts. | F8: Backend | G8: Sprint 1 | H8: 2026-08-23 | I8: GLAccountRepository completed (T-003) | J8: 0.76 | L8: High | N8: Not Started | O8: - GL Account code must be unique per organization; duplicate detection is case-insensitive - Only Active GL Accounts are selectable in any downstream dropdown (e.g., Expense Category form) - A GL Account cannot be deleted while mapped to one or more Expense Categories - Administrator creates a GL Account with a unique code, name, and account type - Admin can create/edit/deactivate a GL Account with a unique code, name and account type - Unit tests passed - UI integrated successfully
A9: T-005 | B9: EP01 - Expense Management System Foundation & Administration | C9: EP01-S1 - Configure GL Account Management | D9: Implement GL Account Service | E9: Implement the GL Account service layer. Business flow: Administrator creates a GL Account with a unique code, name, and account type.; A GL Account becomes selectable for mapping (e.g., by Expense Category) only once its status is Active.; Deactivating a GL Account does not affect categories already mapped to it historically, but prevents new mapping.. Enforce: GL Account code must be unique per organization; duplicate detection is case-insensitive.; Only Active GL Accounts are selectable in any downstream dropdown (e.g., Expense Category form).; A GL Account cannot be deleted while mapped to one or more Expense Categories.. Exceptions: Attempt to delete a GL Account that is mapped to one or more Expense Categories — blocked with an explicit message listing the mapped categories.; Attempt to deactivate a GL Account still mapped to an active Expense Category — allowed, but every mapped category is auto-flagged 'GL Mapping Invalid' until remapped.. | F9: Backend | G9: Sprint 1 | H9: 2026-08-23 | I9: GL Account DTOs completed (T-004) | J9: 1.73 | L9: High | N9: Not Started | O9: - GL Account code must be unique per organization; duplicate detection is case-insensitive - Only Active GL Accounts are selectable in any downstream dropdown (e.g., Expense Category form) - A GL Account cannot be deleted while mapped to one or more Expense Categories - Administrator creates a GL Account with a unique code, name, and account type - Admin can create/edit/deactivate a GL Account with a unique code, name and account type - Unit tests passed - UI integrated successfully
A10: T-006 | B10: EP01 - Expense Management System Foundation & Administration | C10: EP01-S1 - Configure GL Account Management | D10: Implement GL Account CRUD REST APIs | E10: Implement the REST APIs for GL Account Management: POST /api/v1/gl-accounts, PUT /api/v1/gl-accounts/{id}, GET /api/v1/gl-accounts, GET /api/v1/gl-accounts/{id}, DELETE /api/v1/gl-accounts/{id}. Requests must enforce the service-layer validations and return errors per: Attempt to delete a GL Account that is mapped to one or more Expense Categories — blocked with an explicit message listing the mapped categories. | F10: Backend | G10: Sprint 1 | H10: 2026-08-23 | I10: GL Account Service completed (T-005) | J10: 1.3 | L10: High | N10: Not Started | O10: - GL Account code must be unique per organization; duplicate detection is case-insensitive - Only Active GL Accounts are selectable in any downstream dropdown (e.g., Expense Category form) - A GL Account cannot be deleted while mapped to one or more Expense Categories - Administrator creates a GL Account with a unique code, name, and account type - Admin can create/edit/deactivate a GL Account with a unique code, name and account type - Unit tests passed - UI integrated successfully
A11: T-007 | B11: EP01 - Expense Management System Foundation & Administration | C11: EP01-S1 - Configure GL Account Management | D11: Build GL Account Management UI | E11: Build the GL Account Management screen: Tabular GL Account list with inline create/edit and an Active/Inactive status toggle.; Delete action is disabled (with tooltip) on any GL Account currently mapped to an Expense Category. | F11: Frontend | G11: Sprint 1 | H11: 2026-08-23 | I11: GL Account CRUD APIs completed (T-006) | J11: 1.51 | L11: High | N11: Not Started | O11: - GL Account code must be unique per organization; duplicate detection is case-insensitive - Only Active GL Accounts are selectable in any downstream dropdown (e.g., Expense Category form) - A GL Account cannot be deleted while mapped to one or more Expense Categories - Administrator creates a GL Account with a unique code, name, and account type - Admin can create/edit/deactivate a GL Account with a unique code, name and account type - Unit tests passed - UI integrated successfully
A12: T-008 | B12: EP01 - Expense Management System Foundation & Administration | C12: EP01-S1 - Configure GL Account Management | D12: GL Account API Integration | E12: Integrate POST /api/v1/gl-accounts, PUT /api/v1/gl-accounts/{id}, GET /api/v1/gl-accounts, GET /api/v1/gl-accounts/{id}, DELETE /api/v1/gl-accounts/{id} into the GL Account Management UI; wire the Active-only GL Account picker so it can be reused by the Expense Category form, with loading states and error handling for API failures. | F12: Integration | G12: Sprint 1 | H12: 2026-08-23 | I12: GL Account Management UI completed (T-007) | J12: 0.86 | L12: High | N12: Not Started | O12: - GL Account code must be unique per organization; duplicate detection is case-insensitive - Only Active GL Accounts are selectable in any downstream dropdown (e.g., Expense Category form) - A GL Account cannot be deleted while mapped to one or more Expense Categories - Administrator creates a GL Account with a unique code, name, and account type - Admin can create/edit/deactivate a GL Account with a unique code, name and account type - Unit tests passed - UI integrated successfully
A13: T-009 | B13: EP01 - Expense Management System Foundation & Administration | C13: EP01-S1 - Configure GL Account Management | D13: Implement GL Account Validations | E13: Implement validations end-to-end (service + client-mirrored): GL Account code must be unique per organization; duplicate detection is case-insensitive.; Only Active GL Accounts are selectable in any downstream dropdown (e.g., Expense Category form).; A GL Account cannot be deleted while mapped to one or more Expense Categories.. Client-side mirrors of these rules must match the server-side checks exactly. | F13: Backend | G13: Sprint 1 | H13: 2026-08-23 | I13: GL Account API integration completed (T-008) | J13: 0.65 | L13: High | N13: Not Started | O13: - GL Account code must be unique per organization; duplicate detection is case-insensitive - Only Active GL Accounts are selectable in any downstream dropdown (e.g., Expense Category form) - A GL Account cannot be deleted while mapped to one or more Expense Categories - Administrator creates a GL Account with a unique code, name, and account type - Admin can create/edit/deactivate a GL Account with a unique code, name and account type - Unit tests passed - UI integrated successfully
A14: T-010 | B14: EP01 - Expense Management System Foundation & Administration | C14: EP01-S1 - Configure GL Account Management | D14: Unit Testing — GL Account Service & APIs | E14: Write unit tests covering the GL Account service logic, all validations (GL Account code must be unique per organization; duplicate detection is case-insensitive.; Only Active GL Accounts are selectable in any downstream dropdown (e.g., Expense Category form).; A GL Account cannot be deleted while mapped to one or more Expense Categories.), and the REST API contract (POST /api/v1/gl-accounts, PUT /api/v1/gl-accounts/{id}, GET /api/v1/gl-accounts, GET /api/v1/gl-accounts/{id}, DELETE /api/v1/gl-accounts/{id}). | F14: Testing | G14: Sprint 1 | H14: 2026-08-23 | I14: GL Account validations completed (T-009) | J14: 0.54 | L14: High | N14: Not Started | O14: - GL Account code must be unique per organization; duplicate detection is case-insensitive - Only Active GL Accounts are selectable in any downstream dropdown (e.g., Expense Category form) - A GL Account cannot be deleted while mapped to one or more Expense Categories - Administrator creates a GL Account with a unique code, name, and account type - Admin can create/edit/deactivate a GL Account with a unique code, name and account type - Unit tests passed - UI integrated successfully
A15: T-011 | B15: EP01 - Expense Management System Foundation & Administration | C15: EP01-S1 - Configure GL Account Management | D15: Integration Testing — GL Account Management | E15: Write integration tests covering the full GL Account create/edit/deactivate/delete flow end-to-end, including the delete-blocked-while-mapped scenario once Expense Category linkage exists. | F15: Testing | G15: Sprint 1 | H15: 2026-08-23 | I15: GL Account unit tests passed (T-010) | J15: 0.43 | L15: High | N15: Not Started | O15: - GL Account code must be unique per organization; duplicate detection is case-insensitive - Only Active GL Accounts are selectable in any downstream dropdown (e.g., Expense Category form) - A GL Account cannot be deleted while mapped to one or more Expense Categories - Administrator creates a GL Account with a unique code, name, and account type - Admin can create/edit/deactivate a GL Account with a unique code, name and account type - Unit tests passed - UI integrated successfully
A16: T-012 | B16: EP01 - Expense Management System Foundation & Administration | C16: EP01-S1 - Configure GL Account Management | D16: Code Review — GL Account Management | E16: Peer-review the GL Account Management implementation (entity, repository, DTOs, service, APIs, UI), and deploy to the QA environment. | F16: Review/Deployment | G16: Sprint 1 | H16: 2026-08-23 | I16: GL Account integration tests passed (T-011) | J16: 0.22 | L16: High | N16: Not Started | O16: - GL Account code must be unique per organization; duplicate detection is case-insensitive - Only Active GL Accounts are selectable in any downstream dropdown (e.g., Expense Category form) - A GL Account cannot be deleted while mapped to one or more Expense Categories - Administrator creates a GL Account with a unique code, name, and account type - Admin can create/edit/deactivate a GL Account with a unique code, name and account type - Unit tests passed - UI integrated successfully
... A739: T-735 | B739: EP14 - Role-Based Access Control (RBAC) | C739: RBAC-S6 - Admin UI for managing roles and permissions matrix | D739: Code review, documentation & deployment for Role & Permission Configuration | E739: Peer-review the Role & Permission Configuration implementation (entity, repository, service, APIs, UI), update technical documentation, and deploy to the QA environment. | F739: Review/Deployment | G739: Sprint 17 | H739: 2027-04-04 | I739: UI testing passed for Role & Permission Configuration (T-734) | J739: 1.03 | L739: High | N739: Not Started | O739: - A role cannot be deleted while actively assigned to one or more employees; must be reassigned first - At least one Administrator role must always exist in the system (last-admin protection) - Administrator creates or edits a role and assigns a set of granular permissions (e.g., EXPENSE_SUBMIT, EXPE - Admin can view and edit the full permission matrix (roles x modules x actions) in a single screen - Unit tests passed - UI integrated successfully
I740: TOTAL ESTIMATED HOURS | J740: =SUM(J5:J739) -> 837.23 | K740: =SUM(K5:K739) -> 0

Sheet Category Summary
A1: Effort by Category — For Task Assignment Planning
A2: Live counts/hours by task category, pulled from the Project Tracker. Use this to plan who takes which category of work once the team is assigned.
A4: Category | B4: Total Tasks | C4: Not Started | D4: In Progress | E4: Completed | F4: Blocked | G4: Total Est. Hours
A5: Database | B5: =COUNTIF('Project Tracker'!$F$5:$F$739,A5) -> 146 | C5: =COUNTIFS('Project Tracker'!$F$5:$F$739,A5,'Project Tracker'!$N$5:$N$739,"Not Started") -> 146 | D5: =COUNTIFS('Project Tracker'!$F$5:$F$739,A5,'Project Tracker'!$N$5:$N$739,"In Progress") -> 0 | E5: =COUNTIFS('Project Tracker'!$F$5:$F$739,A5,'Project Tracker'!$N$5:$N$739,"Completed") -> 0 | F5: =COUNTIFS('Project Tracker'!$F$5:$F$739,A5,'Project Tracker'!$N$5:$N$739,"Blocked") -> 0 | G5: =SUMIF('Project Tracker'!$F$5:$F$739,A5,'Project Tracker'!$J$5:$J$739) -> 164.31
A6: Backend | B6: =COUNTIF('Project Tracker'!$F$5:$F$739,A6) -> 223 | C6: =COUNTIFS('Project Tracker'!$F$5:$F$739,A6,'Project Tracker'!$N$5:$N$739,"Not Started") -> 223 | D6: =COUNTIFS('Project Tracker'!$F$5:$F$739,A6,'Project Tracker'!$N$5:$N$739,"In Progress") -> 0 | E6: =COUNTIFS('Project Tracker'!$F$5:$F$739,A6,'Project Tracker'!$N$5:$N$739,"Completed") -> 0 | F6: =COUNTIFS('Project Tracker'!$F$5:$F$739,A6,'Project Tracker'!$N$5:$N$739,"Blocked") -> 0 | G6: =SUMIF('Project Tracker'!$F$5:$F$739,A6,'Project Tracker'!$J$5:$J$739) -> 387.01
A7: Frontend | B7: =COUNTIF('Project Tracker'!$F$5:$F$739,A7) -> 73 | C7: =COUNTIFS('Project Tracker'!$F$5:$F$739,A7,'Project Tracker'!$N$5:$N$739,"Not Started") -> 73 | D7: =COUNTIFS('Project Tracker'!$F$5:$F$739,A7,'Project Tracker'!$N$5:$N$739,"In Progress") -> 0 | E7: =COUNTIFS('Project Tracker'!$F$5:$F$739,A7,'Project Tracker'!$N$5:$N$739,"Completed") -> 0 | F7: =COUNTIFS('Project Tracker'!$F$5:$F$739,A7,'Project Tracker'!$N$5:$N$739,"Blocked") -> 0 | G7: =SUMIF('Project Tracker'!$F$5:$F$739,A7,'Project Tracker'!$J$5:$J$739) -> 76.57
A8: Integration | B8: =COUNTIF('Project Tracker'!$F$5:$F$739,A8) -> 74 | C8: =COUNTIFS('Project Tracker'!$F$5:$F$739,A8,'Project Tracker'!$N$5:$N$739,"Not Started") -> 74 | D8: =COUNTIFS('Project Tracker'!$F$5:$F$739,A8,'Project Tracker'!$N$5:$N$739,"In Progress") -> 0 | E8: =COUNTIFS('Project Tracker'!$F$5:$F$739,A8,'Project Tracker'!$N$5:$N$739,"Completed") -> 0 | F8: =COUNTIFS('Project Tracker'!$F$5:$F$739,A8,'Project Tracker'!$N$5:$N$739,"Blocked") -> 0 | G8: =SUMIF('Project Tracker'!$F$5:$F$739,A8,'Project Tracker'!$J$5:$J$739) -> 60.29
A9: Testing | B9: =COUNTIF('Project Tracker'!$F$5:$F$739,A9) -> 146 | C9: =COUNTIFS('Project Tracker'!$F$5:$F$739,A9,'Project Tracker'!$N$5:$N$739,"Not Started") -> 146 | D9: =COUNTIFS('Project Tracker'!$F$5:$F$739,A9,'Project Tracker'!$N$5:$N$739,"In Progress") -> 0 | E9: =COUNTIFS('Project Tracker'!$F$5:$F$739,A9,'Project Tracker'!$N$5:$N$739,"Completed") -> 0 | F9: =COUNTIFS('Project Tracker'!$F$5:$F$739,A9,'Project Tracker'!$N$5:$N$739,"Blocked") -> 0 | G9: =SUMIF('Project Tracker'!$F$5:$F$739,A9,'Project Tracker'!$J$5:$J$739) -> 94.76
A10: Review/Deployment | B10: =COUNTIF('Project Tracker'!$F$5:$F$739,A10) -> 73 | C10: =COUNTIFS('Project Tracker'!$F$5:$F$739,A10,'Project Tracker'!$N$5:$N$739,"Not Started") -> 73 | D10: =COUNTIFS('Project Tracker'!$F$5:$F$739,A10,'Project Tracker'!$N$5:$N$739,"In Progress") -> 0 | E10: =COUNTIFS('Project Tracker'!$F$5:$F$739,A10,'Project Tracker'!$N$5:$N$739,"Completed") -> 0 | F10: =COUNTIFS('Project Tracker'!$F$5:$F$739,A10,'Project Tracker'!$N$5:$N$739,"Blocked") -> 0 | G10: =SUMIF('Project Tracker'!$F$5:$F$739,A10,'Project Tracker'!$J$5:$J$739) -> 54.29
A11: TOTAL | B11: =SUM(B5:B10) -> 735 | C11: =SUM(C5:C10) -> 735 | D11: =SUM(D5:D10) -> 0 | E11: =SUM(E5:E10) -> 0 | F11: =SUM(F5:F10) -> 0 | G11: =SUM(G5:G10) -> 837.23
A14: Tip: filter the Project Tracker sheet by Category and assign the Assignee column once your team is confirmed.

Sheet Epic Overview
A1: Epic Overview & Dependencies
A2: All 14 Epics (13 original + RBAC) with priority, sprint range, dependencies and live hour totals from the Project Tracker.
A4: Epic ID | B4: Epic Name | C4: Priority | D4: Depends On | E4: Sprint Range | F4: Estimated Hours | G4: % of Total Hours
A5: EP01 | B5: Expense Management System Foundation & Administration | C5: High | D5: None (first Epic) | E5: Sprint 1-2 | F5: =SUMIF('Project Tracker'!$B$5:$B$739,"EP01*",'Project Tracker'!$J$5:$J$739) -> 54.09 | G5: =F5/$F$19 -> 0.064605903
A6: EP02 | B6: Expense Report & Line Item Management | C6: High | D6: EP01 | E6: Sprint 2-4 | F6: =SUMIF('Project Tracker'!$B$5:$B$739,"EP02*",'Project Tracker'!$J$5:$J$739) -> 91.91 | G6: =F6/$F$19 -> 0.10977867
A7: EP09 | B7: Cost Center & Expense Allocation Management | C7: Medium | D7: EP01 | E7: Sprint 4-5 | F7: =SUMIF('Project Tracker'!$B$5:$B$739,"EP09*",'Project Tracker'!$J$5:$J$739) -> 43.22 | G7: =F7/$F$19 -> 0.051622613
A8: EP03 | B8: Receipt Management & OCR Processing | C8: Medium | D8: EP02 | E8: Sprint 5 | F8: =SUMIF('Project Tracker'!$B$5:$B$739,"EP03*",'Project Tracker'!$J$5:$J$739) -> 48.53 | G8: =F8/$F$19 -> 0.057964956
A9: EP05 | B9: Expense Policy & Compliance Management | C9: Medium | D9: EP01, EP02 | E9: Sprint 6 | F9: =SUMIF('Project Tracker'!$B$5:$B$739,"EP05*",'Project Tracker'!$J$5:$J$739) -> 48.62 | G9: =F9/$F$19 -> 0.058072453
A10: EP04 | B10: Cash Advance Management | C10: Medium | D10: EP01, EP02 | E10: Sprint 7 | F10: =SUMIF('Project Tracker'!$B$5:$B$739,"EP04*",'Project Tracker'!$J$5:$J$739) -> 54.11 | G10: =F10/$F$19 -> 0.064629791
A11: EP06 | B11: Expense Approval Workflow Management | C11: High | D11: EP02, EP05 | E11: Sprint 8-9 | F11: =SUMIF('Project Tracker'!$B$5:$B$739,"EP06*",'Project Tracker'!$J$5:$J$739) -> 70.32 | G11: =F11/$F$19 -> 0.083991257
A12: EP07 | B12: Finance Verification & Reimbursement Management | C12: High | D12: EP06 | E12: Sprint 9-10 | F12: =SUMIF('Project Tracker'!$B$5:$B$739,"EP07*",'Project Tracker'!$J$5:$J$739) -> 64.84 | G12: =F12/$F$19 -> 0.077445863
A13: EP08 | B13: Client Billable Expense & Invoice Integration | C13: Medium | D13: EP07, EP09 | E13: Sprint 10-11 | F13: =SUMIF('Project Tracker'!$B$5:$B$739,"EP08*",'Project Tracker'!$J$5:$J$739) -> 70.12 | G13: =F13/$F$19 -> 0.083752374
A14: EP13 | B14: System Integrations | C14: Medium | D14: EP01, EP02, EP03, EP04, EP08, EP09 | E14: Sprint 11-12 | F14: =SUMIF('Project Tracker'!$B$5:$B$739,"EP13*",'Project Tracker'!$J$5:$J$739) -> 58.96 | G14: =F14/$F$19 -> 0.070422703
A15: EP11 | B15: Notifications, Audit Logs & Activity Tracking | C15: Low | D15: EP06, EP07 | E15: Sprint 12-13 | F15: =SUMIF('Project Tracker'!$B$5:$B$739,"EP11*",'Project Tracker'!$J$5:$J$739) -> 48.62 | G15: =F15/$F$19 -> 0.058072453
A16: EP10 | B16: Dashboard, Reporting & Analytics | C16: Low | D16: EP02, EP06, EP07, EP08, EP09 | E16: Sprint 13-14 | F16: =SUMIF('Project Tracker'!$B$5:$B$739,"EP10*",'Project Tracker'!$J$5:$J$739) -> 59.02 | G16: =F16/$F$19 -> 0.070494368
A17: EP12 | B17: Search, Filters & Expense Tracking | C17: Low | D17: EP02, EP04, EP06, EP07, EP08 | E17: Sprint 14-15 | F17: =SUMIF('Project Tracker'!$B$5:$B$739,"EP12*",'Project Tracker'!$J$5:$J$739) -> 37.65 | G17: =F17/$F$19 -> 0.044969722
A18: EP14 | B18: Role-Based Access Control (RBAC) | C18: High | D18: EP01 | E18: Sprint 16-17 | F18: =SUMIF('Project Tracker'!$B$5:$B$739,"EP14*",'Project Tracker'!$J$5:$J$739) -> 87.22 | G18: =F18/$F$19 -> 0.10417687
B19: TOTAL | F19: =SUM(F5:F18) -> 837.23 | G19: 1

Sheet Sprint Summary
A1: Sprint-by-Sprint Progress
A2: Live totals pulled from the Project Tracker sheet — update Status there and these numbers refresh automatically.
A4: Sprint | B4: Total Tasks | C4: Completed | D4: In Progress | E4: Not Started / Blocked | F4: Estimated Hours
A5: Sprint 1 | B5: =COUNTIF('Project Tracker'!$G$5:$G$739,A5) -> 52 | C5: =COUNTIFS('Project Tracker'!$G$5:$G$739,A5,'Project Tracker'!$N$5:$N$739,"Completed") -> 0 | D5: =COUNTIFS('Project Tracker'!$G$5:$G$739,A5,'Project Tracker'!$N$5:$N$739,"In Progress") -> 0 | E5: =COUNTIFS('Project Tracker'!$G$5:$G$739,A5,'Project Tracker'!$N$5:$N$739,"Not Started")+COUNTIFS('Project Tracker'!$G$5:$G$739,A5,'Project Tracker'!$N$5:$N$739,"Blocked") -> 52 | F5: =SUMIF('Project Tracker'!$G$5:$G$739,A5,'Project Tracker'!$J$5:$J$739) -> 49.76
A6: Sprint 2 | B6: =COUNTIF('Project Tracker'!$G$5:$G$739,A6) -> 30 | C6: =COUNTIFS('Project Tracker'!$G$5:$G$739,A6,'Project Tracker'!$N$5:$N$739,"Completed") -> 0 | D6: =COUNTIFS('Project Tracker'!$G$5:$G$739,A6,'Project Tracker'!$N$5:$N$739,"In Progress") -> 0 | E6: =COUNTIFS('Project Tracker'!$G$5:$G$739,A6,'Project Tracker'!$N$5:$N$739,"Not Started")+COUNTIFS('Project Tracker'!$G$5:$G$739,A6,'Project Tracker'!$N$5:$N$739,"Blocked") -> 30 | F6: =SUMIF('Project Tracker'!$G$5:$G$739,A6,'Project Tracker'!$J$5:$J$739) -> 39.51
A7: Sprint 3 | B7: =COUNTIF('Project Tracker'!$G$5:$G$739,A7) -> 30 | C7: =COUNTIFS('Project Tracker'!$G$5:$G$739,A7,'Project Tracker'!$N$5:$N$739,"Completed") -> 0 | D7: =COUNTIFS('Project Tracker'!$G$5:$G$739,A7,'Project Tracker'!$N$5:$N$739,"In Progress") -> 0 | E7: =COUNTIFS('Project Tracker'!$G$5:$G$739,A7,'Project Tracker'!$N$5:$N$739,"Not Started")+COUNTIFS('Project Tracker'!$G$5:$G$739,A7,'Project Tracker'!$N$5:$N$739,"Blocked") -> 30 | F7: =SUMIF('Project Tracker'!$G$5:$G$739,A7,'Project Tracker'!$J$5:$J$739) -> 48.68
A8: Sprint 4 | B8: =COUNTIF('Project Tracker'!$G$5:$G$739,A8) -> 40 | C8: =COUNTIFS('Project Tracker'!$G$5:$G$739,A8,'Project Tracker'!$N$5:$N$739,"Completed") -> 0 | D8: =COUNTIFS('Project Tracker'!$G$5:$G$739,A8,'Project Tracker'!$N$5:$N$739,"In Progress") -> 0 | E8: =COUNTIFS('Project Tracker'!$G$5:$G$739,A8,'Project Tracker'!$N$5:$N$739,"Not Started")+COUNTIFS('Project Tracker'!$G$5:$G$739,A8,'Project Tracker'!$N$5:$N$739,"Blocked") -> 40 | F8: =SUMIF('Project Tracker'!$G$5:$G$739,A8,'Project Tracker'!$J$5:$J$739) -> 45.91
A9: Sprint 5 | B9: =COUNTIF('Project Tracker'!$G$5:$G$739,A9) -> 50 | C9: =COUNTIFS('Project Tracker'!$G$5:$G$739,A9,'Project Tracker'!$N$5:$N$739,"Completed") -> 0 | D9: =COUNTIFS('Project Tracker'!$G$5:$G$739,A9,'Project Tracker'!$N$5:$N$739,"In Progress") -> 0 | E9: =COUNTIFS('Project Tracker'!$G$5:$G$739,A9,'Project Tracker'!$N$5:$N$739,"Not Started")+COUNTIFS('Project Tracker'!$G$5:$G$739,A9,'Project Tracker'!$N$5:$N$739,"Blocked") -> 50 | F9: =SUMIF('Project Tracker'!$G$5:$G$739,A9,'Project Tracker'!$J$5:$J$739) -> 53.89
A10: Sprint 6 | B10: =COUNTIF('Project Tracker'!$G$5:$G$739,A10) -> 50 | C10: =COUNTIFS('Project Tracker'!$G$5:$G$739,A10,'Project Tracker'!$N$5:$N$739,"Completed") -> 0 | D10: =COUNTIFS('Project Tracker'!$G$5:$G$739,A10,'Project Tracker'!$N$5:$N$739,"In Progress") -> 0 | E10: =COUNTIFS('Project Tracker'!$G$5:$G$739,A10,'Project Tracker'!$N$5:$N$739,"Not Started")+COUNTIFS('Project Tracker'!$G$5:$G$739,A10,'Project Tracker'!$N$5:$N$739,"Blocked") -> 50 | F10: =SUMIF('Project Tracker'!$G$5:$G$739,A10,'Project Tracker'!$J$5:$J$739) -> 48.62
A11: Sprint 7 | B11: =COUNTIF('Project Tracker'!$G$5:$G$739,A11) -> 50 | C11: =COUNTIFS('Project Tracker'!$G$5:$G$739,A11,'Project Tracker'!$N$5:$N$739,"Completed") -> 0 | D11: =COUNTIFS('Project Tracker'!$G$5:$G$739,A11,'Project Tracker'!$N$5:$N$739,"In Progress") -> 0 | E11: =COUNTIFS('Project Tracker'!$G$5:$G$739,A11,'Project Tracker'!$N$5:$N$739,"Not Started")+COUNTIFS('Project Tracker'!$G$5:$G$739,A11,'Project Tracker'!$N$5:$N$739,"Blocked") -> 50 | F11: =SUMIF('Project Tracker'!$G$5:$G$739,A11,'Project Tracker'!$J$5:$J$739) -> 54.11
A12: Sprint 8 | B12: =COUNTIF('Project Tracker'!$G$5:$G$739,A12) -> 30 | C12: =COUNTIFS('Project Tracker'!$G$5:$G$739,A12,'Project Tracker'!$N$5:$N$739,"Completed") -> 0 | D12: =COUNTIFS('Project Tracker'!$G$5:$G$739,A12,'Project Tracker'!$N$5:$N$739,"In Progress") -> 0 | E12: =COUNTIFS('Project Tracker'!$G$5:$G$739,A12,'Project Tracker'!$N$5:$N$739,"Not Started")+COUNTIFS('Project Tracker'!$G$5:$G$739,A12,'Project Tracker'!$N$5:$N$739,"Blocked") -> 30 | F12: =SUMIF('Project Tracker'!$G$5:$G$739,A12,'Project Tracker'!$J$5:$J$739) -> 48.7
A13: Sprint 9 | B13: =COUNTIF('Project Tracker'!$G$5:$G$739,A13) -> 63 | C13: =COUNTIFS('Project Tracker'!$G$5:$G$739,A13,'Project Tracker'!$N$5:$N$739,"Completed") -> 0 | D13: =COUNTIFS('Project Tracker'!$G$5:$G$739,A13,'Project Tracker'!$N$5:$N$739,"In Progress") -> 0 | E13: =COUNTIFS('Project Tracker'!$G$5:$G$739,A13,'Project Tracker'!$N$5:$N$739,"Not Started")+COUNTIFS('Project Tracker'!$G$5:$G$739,A13,'Project Tracker'!$N$5:$N$739,"Blocked") -> 63 | F13: =SUMIF('Project Tracker'!$G$5:$G$739,A13,'Project Tracker'!$J$5:$J$739) -> 59.51
A14: Sprint 10 | B14: =COUNTIF('Project Tracker'!$G$5:$G$739,A14) -> 50 | C14: =COUNTIFS('Project Tracker'!$G$5:$G$739,A14,'Project Tracker'!$N$5:$N$739,"Completed") -> 0 | D14: =COUNTIFS('Project Tracker'!$G$5:$G$739,A14,'Project Tracker'!$N$5:$N$739,"In Progress") -> 0 | E14: =COUNTIFS('Project Tracker'!$G$5:$G$739,A14,'Project Tracker'!$N$5:$N$739,"Not Started")+COUNTIFS('Project Tracker'!$G$5:$G$739,A14,'Project Tracker'!$N$5:$N$739,"Blocked") -> 50 | F14: =SUMIF('Project Tracker'!$G$5:$G$739,A14,'Project Tracker'!$J$5:$J$739) -> 56.73
A15: Sprint 11 | B15: =COUNTIF('Project Tracker'!$G$5:$G$739,A15) -> 40 | C15: =COUNTIFS('Project Tracker'!$G$5:$G$739,A15,'Project Tracker'!$N$5:$N$739,"Completed") -> 0 | D15: =COUNTIFS('Project Tracker'!$G$5:$G$739,A15,'Project Tracker'!$N$5:$N$739,"In Progress") -> 0 | E15: =COUNTIFS('Project Tracker'!$G$5:$G$739,A15,'Project Tracker'!$N$5:$N$739,"Not Started")+COUNTIFS('Project Tracker'!$G$5:$G$739,A15,'Project Tracker'!$N$5:$N$739,"Blocked") -> 40 | F15: =SUMIF('Project Tracker'!$G$5:$G$739,A15,'Project Tracker'!$J$5:$J$739) -> 53.75
A16: Sprint 12 | B16: =COUNTIF('Project Tracker'!$G$5:$G$739,A16) -> 60 | C16: =COUNTIFS('Project Tracker'!$G$5:$G$739,A16,'Project Tracker'!$N$5:$N$739,"Completed") -> 0 | D16: =COUNTIFS('Project Tracker'!$G$5:$G$739,A16,'Project Tracker'!$N$5:$N$739,"In Progress") -> 0 | E16: =COUNTIFS('Project Tracker'!$G$5:$G$739,A16,'Project Tracker'!$N$5:$N$739,"Not Started")+COUNTIFS('Project Tracker'!$G$5:$G$739,A16,'Project Tracker'!$N$5:$N$739,"Blocked") -> 60 | F16: =SUMIF('Project Tracker'!$G$5:$G$739,A16,'Project Tracker'!$J$5:$J$739) -> 59.07
... A21: Sprint 17 | B21: =COUNTIF('Project Tracker'!$G$5:$G$739,A21) -> 30 | C21: =COUNTIFS('Project Tracker'!$G$5:$G$739,A21,'Project Tracker'!$N$5:$N$739,"Completed") -> 0 | D21: =COUNTIFS('Project Tracker'!$G$5:$G$739,A21,'Project Tracker'!$N$5:$N$739,"In Progress") -> 0 | E21: =COUNTIFS('Project Tracker'!$G$5:$G$739,A21,'Project Tracker'!$N$5:$N$739,"Not Started")+COUNTIFS('Project Tracker'!$G$5:$G$739,A21,'Project Tracker'!$N$5:$N$739,"Blocked") -> 30 | F21: =SUMIF('Project Tracker'!$G$5:$G$739,A21,'Project Tracker'!$J$5:$J$739) -> 39.12
A22: TOTAL | B22: =SUM(B5:B21) -> 735 | C22: =SUM(C5:C21) -> 0 | D22: =SUM(D5:D21) -> 0 | E22: =SUM(E5:E21) -> 735 | F22: =SUM(F5:F21) -> 837.23
